Metadata-Version: 2.4
Name: sigmap-polygeohasher
Version: 0.0.3
Summary: Python package that allow you to download and manipulate geometries by subdivising it using geohash.
Project-URL: Homepage, https://github.com/WillHCode/Sigmap-PolyGeohasher
Project-URL: Documentation, https://sigmap-polygeohasher.readthedocs.io/
Project-URL: Issues, https://github.com/WillHCode/Sigmap-PolyGeohasher/issues
Author: Hubaux William
License: BSD 3-Clause
Classifier: Intended Audience :: Developers
Classifier: Intended Audience :: Science/Research
Classifier: License :: OSI Approved :: BSD License
Classifier: Operating System :: OS Independent
Classifier: Programming Language :: Python :: 3
Classifier: Topic :: Scientific/Engineering :: GIS
Requires-Python: >=3.12
Requires-Dist: geopandas>=1.1.1
Requires-Dist: matplotlib
Requires-Dist: numpy>=2.3.3
Requires-Dist: pandas>=2.3.3
Requires-Dist: requests>=2.32.5
Requires-Dist: shapely>=2.1.2
Provides-Extra: docs
Requires-Dist: sphinx-autodoc-typehints>=1.24.0; extra == 'docs'
Requires-Dist: sphinx-book-theme>=1.0.0; extra == 'docs'
Requires-Dist: sphinx>=7.0.0; extra == 'docs'
